binance_aiohttp/__init__.py
binance_aiohttp/client.py
binance_aiohttp-0.0.5.dist-info/LICENSE
binance_aiohttp-0.0.5.dist-info/METADATA
binance_aiohttp-0.0.5.dist-info/WHEEL
binance_aiohttp-0.0.5.dist-info/top_level.txt
binance_aiohttp-0.0.5.dist-info/RECORD
