Metadata-Version: 2.1
Name: binance-aiohttp
Version: 0.0.5
Summary: asynchronous binance client based on asyncio and aiohttp
Home-page: https://github.com/m-abdi/asynchronous_binance_client
Author: Mehdi Abdi
Author-email: m.abdi.public@gmail.com
License: UNKNOWN
Project-URL: Bug Tracker, https://github.com/pypa/sampleproject/issues
Platform: UNKNOWN
Classifier: Programming Language :: Python :: 3.9
Classifier: License :: OSI Approved :: MIT License
Classifier: Operating System :: OS Independent
Requires-Python: >=3.9
License-File: LICENSE
Requires-Dist: aiohttp
Requires-Dist: ujson
